nengo_bio/__init__.py
nengo_bio/common.py
nengo_bio/config.py
nengo_bio/connection.py
nengo_bio/ensemble.py
nengo_bio/neurons.py
nengo_bio/solvers.py
nengo_bio/builder/__init__.py
nengo_bio/builder/connection.py
nengo_bio/builder/ensemble.py
nengo_bio/builder/neurons.py
nengo_bio/internal/__init__.py
nengo_bio/internal/env_guard.py
nengo_bio/internal/lif_utils.py
nengo_bio/internal/model_weights.py
nengo_bio/internal/multi_compartment_lif.hpp
nengo_bio/internal/multi_compartment_lif_cpp.py
nengo_bio/internal/multi_compartment_lif_parameters.py
nengo_bio/internal/multi_compartment_lif_python.py
nengo_bio/internal/multi_compartment_lif_sim.py
nengo_bio/internal/qp_solver.py
nengo_bio-0.2.0.dist-info/LICENSE.txt
nengo_bio-0.2.0.dist-info/METADATA
nengo_bio-0.2.0.dist-info/WHEEL
nengo_bio-0.2.0.dist-info/top_level.txt
nengo_bio-0.2.0.dist-info/RECORD
