Metadata-Version: 2.1
Name: nengo-bio
Version: 0.2.0
Summary: Dendritic Computation Primitives for Nengo
Home-page: https://github.com/astoeckel/nengo-bio
Author: Andreas Stöckel
Author-email: astoecke@uwaterloo.ca
License: GPLv3
Platform: UNKNOWN
Classifier: Development Status :: 3 - Alpha
Classifier: Intended Audience :: Science/Research
Classifier: License :: OSI Approved :: GNU General Public License v3 (GPLv3)
Classifier: Programming Language :: Python :: 3
Classifier: Topic :: Scientific/Engineering
Requires-Dist: cvxopt (>=1.2.2)
Requires-Dist: nengo (>=2.8)
Requires-Dist: numpy (>=1.16.3)
Requires-Dist: scipy (>=1.2.0)
Requires-Dist: posix-ipc (>=1.0.4)
